format_ipy_cells/__init__.py
format_ipy_cells/helpers.py
format_ipy_cells/main.py
format_ipy_cells-0.1.11.dist-info/METADATA
format_ipy_cells-0.1.11.dist-info/WHEEL
format_ipy_cells-0.1.11.dist-info/entry_points.txt
format_ipy_cells-0.1.11.dist-info/top_level.txt
format_ipy_cells-0.1.11.dist-info/RECORD
