Metadata-Version: 2.1
Name: format-ipy-cells
Version: 0.1.11
Summary: Format cells in interactive Python notebooks.
Author-email: Janosh Riebesell <janosh.riebesell@gmail.com>
License: MIT License
Project-URL: Homepage, https://github.com/janosh/format-ipy-cells
Project-URL: Package, https://pypi.org/project/format-ipy-cells
Keywords: code formatting,interactive,ipython,jupyter,pre-commit hook,python
Classifier: License :: OSI Approved :: MIT License
Classifier: Programming Language :: Python :: 3 :: Only
Classifier: Programming Language :: Python :: 3.10
Classifier: Programming Language :: Python :: 3.11
Requires-Python: >=3.10
Provides-Extra: test
Requires-Dist: pytest ; extra == 'test'
Requires-Dist: pytest-cov ; extra == 'test'
